package_desafio_DIO/__init__.py
package_desafio_DIO/processing/__init__.py
package_desafio_DIO/processing/combination.py
package_desafio_DIO/processing/transformation.py
package_desafio_DIO/utils/__init__.py
package_desafio_DIO/utils/io.py
package_desafio_DIO/utils/plot.py
package_desafio_dio-0.0.2.dist-info/METADATA
package_desafio_dio-0.0.2.dist-info/WHEEL
package_desafio_dio-0.0.2.dist-info/top_level.txt
package_desafio_dio-0.0.2.dist-info/RECORD
