Metadata-Version: 2.2
Name: package_desafio_DIO
Version: 0.0.2
Summary: estudo de criação de pacotes
Home-page: https://github.com/nhoblumer/desafio_estudo.git
Author: Nelson Henrique
Author-email: nhoblumer@hotmail.com
Requires-Python: >=3.8
Requires-Dist: numpy
Requires-Dist: scikit-image>=0.16.1
Requires-Dist: matplotlib
Dynamic: author
Dynamic: author-email
Dynamic: description
Dynamic: description-content-type
Dynamic: home-page
Dynamic: requires-dist
Dynamic: requires-python
Dynamic: summary
